jtyoui/__init__.py
jtyoui/cdocker.py
jtyoui/constant.py
jtyoui/fileformat.py
jtyoui/nation.py
jtyoui/surname.py
jtyoui/timezone.py
jtyoui/windows.py
jtyoui-2020.7.8.dist-info/LICENSE
jtyoui-2020.7.8.dist-info/METADATA
jtyoui-2020.7.8.dist-info/WHEEL
jtyoui-2020.7.8.dist-info/top_level.txt
jtyoui-2020.7.8.dist-info/RECORD
