Metadata-Version: 2.1
Name: jtyoui
Version: 2020.7.8
Summary: 这是一个Python集合包,包含了:113个模块。
Home-page: https://github.com/jtyoui/Jtyoui
Author: Jtyoui
Author-email: jtyoui@qq.com
License: MIT Licence
Platform: window10
Platform: Linux
Classifier: Programming Language :: Python :: 3
Classifier: Programming Language :: Python :: 3.6
Classifier: Programming Language :: Python :: 3.7
Classifier: Programming Language :: Python :: 3.8
Classifier: License :: OSI Approved :: MIT License
Classifier: Operating System :: OS Independent
Requires-Dist: pyunit-address (==2020.6.19)
Requires-Dist: pyunit-calendar (==2020.6.2)
Requires-Dist: pyunit-color (==2020.2.11)
Requires-Dist: pyunit-gof (==2020.3.11)
Requires-Dist: pyunit-idcard (==2020.6.22)
Requires-Dist: pyunit-log (==2020.2.10)
Requires-Dist: pyunit-map (==2020.6.17)
Requires-Dist: pyunit-phone (==2020.6.28)
Requires-Dist: pyunit-plate (==2020.6.17)
Requires-Dist: pyunit-prime (==2020.3.22)
Requires-Dist: pyunit-sogou (==2019.1.24)
Requires-Dist: pyunit-string (==2020.4.10)
Requires-Dist: pyunit-time (==2020.4.27)
Requires-Dist: pyunit-tool (==2020.3.10)
Requires-Dist: pyunit-weather (==2019.3.1)
